kantts/__init__.py
kantts-0.1.0.dist-info/METADATA
kantts-0.1.0.dist-info/WHEEL
kantts-0.1.0.dist-info/top_level.txt
kantts-0.1.0.dist-info/RECORD
